datamaker/CSVGenerator.py
datamaker/CodeGenLogic.py
datamaker/DataGenerator.py
datamaker/JSONGenerator.py
datamaker/SQLTableGenerator.py
datamaker/ValidationLogic.py
datamaker/__init__.py
datamaker/common/Common.py
datamaker/common/__init__.py
datamaker/common/paths.py
datamaker/common/metadata/formats.json
datamaker/common/metadata/parameters.json
datamaker/common/static/cities.json
datamaker/common/static/countries.json
datamaker/common/static/names.json
datamaker/common/static/states.json
datamaker/common/static/streets.json
datamaker-1.0.1.data/data/metadata/formats.json
datamaker-1.0.1.data/data/metadata/parameters.json
datamaker-1.0.1.data/data/static/cities.json
datamaker-1.0.1.data/data/static/countries.json
datamaker-1.0.1.data/data/static/names.json
datamaker-1.0.1.data/data/static/states.json
datamaker-1.0.1.data/data/static/streets.json
datamaker-1.0.1.dist-info/LICENSE
datamaker-1.0.1.dist-info/METADATA
datamaker-1.0.1.dist-info/WHEEL
datamaker-1.0.1.dist-info/top_level.txt
datamaker-1.0.1.dist-info/RECORD
