Metadata-Version: 2.1
Name: datamaker
Version: 1.0.1
Summary: A package for generating tabluar datasets
Home-page: https://github.com/tekkabroley/DataMaker
Author: Alex Broley
Author-email: alex.broley@gmail.com
License: UNKNOWN
Platform: UNKNOWN
Classifier: Programming Language :: Python :: 3
Classifier: License :: OSI Approved :: MIT License
Classifier: Operating System :: OS Independent
Requires-Python: >=3.6
